chatgpt_long_term_memory/__init__.py
chatgpt_long_term_memory/conversation/__init__.py
chatgpt_long_term_memory/conversation/chatgpt_chatbot_client.py
chatgpt_long_term_memory/conversation/chatgpt_index_client.py
chatgpt_long_term_memory/llama_index_helpers/__init__.py
chatgpt_long_term_memory/llama_index_helpers/config.py
chatgpt_long_term_memory/llama_index_helpers/index_engine.py
chatgpt_long_term_memory/llama_index_helpers/retrievers_engine.py
chatgpt_long_term_memory/memory/__init__.py
chatgpt_long_term_memory/memory/chat_memory.py
chatgpt_long_term_memory/memory/config.py
chatgpt_long_term_memory/openai_engine/__init__.py
chatgpt_long_term_memory/openai_engine/config.py
chatgpt_long_term_memory/openai_engine/create_context.py
chatgpt_long_term_memory/openai_engine/error_handler.py
chatgpt_long_term_memory/openai_engine/openai_chatbot.py
chatgpt_long_term_memory/openai_engine/token_counter.py
chatgpt_long_term_memory-0.1.0.dist-info/METADATA
chatgpt_long_term_memory-0.1.0.dist-info/WHEEL
chatgpt_long_term_memory-0.1.0.dist-info/top_level.txt
chatgpt_long_term_memory-0.1.0.dist-info/RECORD
