Metadata-Version: 2.1
Name: chatgpt-long-term-memory
Version: 0.1.0
Summary: The ChatGPT Long Term Memory package is a powerful tool designed to empower your projects with the ability to handle a large number of simultaneous users. 
Author: Elmira Ghorbani
Project-URL: Github, https://github.com/ElmiraGhorbani/chatgpt-long-term-memory
Requires-Dist: redis-chatgpt (>=0.1.2)
Requires-Dist: llama-index (>=0.7.9)
Requires-Dist: openai (>=0.27.8)
Requires-Dist: tiktoken (>=0.4.0)
